BENCHMARK_RESULTS.md
LICENSE
MANIFEST.in
Makefile
README.md
README_POSTGRES.md
bm25.go
bm25_test.go
build_package.py
database_schema.sql
go.mod
go.sum
go_vs_bm25s_benchmark.py
main.go
parameter_comparison.py
pyproject.toml
requirements.txt
setup.py
simple_test.py
test_exact_match.py
test_go_direct.py
test_score_comparison.py
./bm25/__init__.py
./bm25/bm25.py
./bm25/bm25s_compat.py
bm25/__init__.py
bm25/bm25.py
bm25/bm25s_compat.py
example/compound_token_example.go
example/optimization_example.go
go_bm25.egg-info/PKG-INFO
go_bm25.egg-info/SOURCES.txt
go_bm25.egg-info/dependency_links.txt
go_bm25.egg-info/entry_points.txt
go_bm25.egg-info/not-zip-safe
go_bm25.egg-info/requires.txt
go_bm25.egg-info/top_level.txt