Metadata-Version: 2.4
Name: go-bm25
Version: 0.2.9
Summary: High-performance BM25 ranking algorithm implementation with Go core and Python bindings
Home-page: https://github.com/pentney/go-bm25
Author: BM25 Contributors
Maintainer: BM25 Contributors
License: MIT
Project-URL: Homepage, https://github.com/pentney/go-bm25
Project-URL: Documentation, https://github.com/pentney/go-bm25#readme
Project-URL: Repository, https://github.com/pentney/go-bm25
Project-URL: Bug Tracker, https://github.com/pentney/go-bm25/issues
Keywords: bm25,search,ranking,information-retrieval,go,python-bindings
Classifier: Development Status :: 3 - Alpha
Classifier: Intended Audience :: Developers
Classifier: Intended Audience :: Science/Research
Classifier: License :: OSI Approved :: MIT License
Classifier: Operating System :: OS Independent
Classifier: Programming Language :: Python :: 3
Classifier: Programming Language :: Python :: 3.8
Classifier: Programming Language :: Python :: 3.9
Classifier: Programming Language :: Python :: 3.10
Classifier: Programming Language :: Python :: 3.11
Classifier: Programming Language :: Python :: 3.12
Classifier: Topic :: Scientific/Engineering :: Information Analysis
Classifier: Topic :: Software Development :: Libraries :: Python Modules
Classifier: Topic :: Text Processing :: Linguistic
Requires-Python: >=3.8
License-File: LICENSE
Requires-Dist: rank-bm25>=0.2.2
Requires-Dist: matplotlib>=3.5.0
Requires-Dist: numpy>=1.21.0
Provides-Extra: dev
Requires-Dist: pytest>=6.0; extra == "dev"
Requires-Dist: pytest-cov>=2.0; extra == "dev"
Requires-Dist: black>=22.0; extra == "dev"
Requires-Dist: flake8>=4.0; extra == "dev"
Requires-Dist: mypy>=0.950; extra == "dev"
Provides-Extra: docs
Requires-Dist: sphinx>=4.0; extra == "docs"
Requires-Dist: sphinx-rtd-theme>=1.0; extra == "docs"
Dynamic: home-page
Dynamic: license-file
Dynamic: requires-python
